datastoresender/__init__.py
datastoresender/client.py
datastoresender/exceptions.py
datastoresender/iterutils.py
datastoresender/model.py
datastoresender/status.py
datastoresender-0.1.0.dist-info/METADATA
datastoresender-0.1.0.dist-info/WHEEL
datastoresender-0.1.0.dist-info/top_level.txt
datastoresender-0.1.0.dist-info/RECORD
